{
	"id": "e19de4e1-1cbf-d30a-7234-84672dad12c3",
	"name": "Eva requests",
	"description": "",
	"order": [],
	"folders": [
		{
			"id": "7f762bcc-bcb9-b98a-a937-f2adc2e3124d",
			"name": "Category",
			"description": "",
			"order": [
				"695ae37b-7dd5-8e1b-9438-2728ebf7f8e7",
				"46504912-6514-fab2-804a-a0c4cf832884",
				"2fc186c5-d3c9-1b71-ead2-59c8848ac7ff",
				"fc9d9a7b-4859-96be-cd8b-7d32b008f5e1",
				"0d172169-14b8-4041-67a1-9edb409c96bc",
				"f02280a0-46d0-70c3-d945-58ab174095e5",
				"593e57d3-8737-3bcb-586d-dd4923b1f8ef"
			],
			"owner": ""
		},
		{
			"id": "8993692f-320b-9faa-24d0-dd4d2f364a16",
			"name": "Challenge",
			"description": "",
			"order": [
				"18cf704c-0f7b-67bf-d254-74a2a3797414",
				"f8f502e4-da76-237f-36ac-8facd2f2f782",
				"e4bb90c3-c4b7-b875-7664-69b797344d6d",
				"7829ea83-b758-1854-9e89-9b8f1d0fc13e",
				"fe02e771-9e6f-ad5e-5dfa-ed1e30be26e0"
			],
			"owner": ""
		},
		{
			"id": "1dca47c6-0346-9fd3-5f90-9bd8211a800c",
			"name": "User",
			"description": "",
			"order": [
				"5d2d7bf8-2e32-a797-5997-f6fd675b8f0d",
				"b64bfb0b-12e0-a151-7bff-2df352876ca6",
				"cc3978f7-bc51-3215-76d5-5b4d69c7f6a0",
				"7f2e7cad-0353-41f7-e30c-e94d8b8c7e57",
				"4a7d6965-fbe4-b0f6-9300-5aaff9a3eefc",
				"585d90d5-91d5-0f5e-7683-c284cd52dabf"
			],
			"owner": ""
		}
	],
	"timestamp": 1444042379314,
	"owner": "",
	"remoteLink": "",
	"public": false,
	"requests": [
		{
			"id": "0d172169-14b8-4041-67a1-9edb409c96bc",
			"headers": "",
			"url": "http://95.85.59.29:1337/api/categories/:id",
			"pathVariables": {
				"id": null
			},
			"preRequestScript": "",
			"method": "DELETE",
			"collectionId": "e19de4e1-1cbf-d30a-7234-84672dad12c3",
			"data": [],
			"dataMode": "raw",
			"name": "Delete category",
			"description": "",
			"descriptionFormat": "html",
			"time": 1445694343265,
			"version": 2,
			"responses": [],
			"tests": "",
			"currentHelper": "normal",
			"helperAttributes": {},
			"folder": "7f762bcc-bcb9-b98a-a937-f2adc2e3124d",
			"rawModeData": ""
		},
		{
			"id": "18cf704c-0f7b-67bf-d254-74a2a3797414",
			"headers": "",
			"url": "http://95.85.59.29:1337/api/challenges",
			"pathVariables": {},
			"preRequestScript": "",
			"method": "GET",
			"collectionId": "e19de4e1-1cbf-d30a-7234-84672dad12c3",
			"data": [],
			"dataMode": "raw",
			"name": "Get all challenges",
			"description": "",
			"descriptionFormat": "html",
			"time": 1445253723340,
			"version": 2,
			"responses": [],
			"tests": "",
			"currentHelper": "normal",
			"helperAttributes": {},
			"folder": "8993692f-320b-9faa-24d0-dd4d2f364a16",
			"rawModeData": ""
		},
		{
			"id": "2fc186c5-d3c9-1b71-ead2-59c8848ac7ff",
			"headers": "",
			"url": "http://95.85.59.29:1337/api/categories/:id/challenges",
			"pathVariables": {
				"id": null
			},
			"preRequestScript": "",
			"method": "GET",
			"collectionId": "e19de4e1-1cbf-d30a-7234-84672dad12c3",
			"data": [],
			"dataMode": "params",
			"name": "Get all challenges from a category",
			"description": "",
			"descriptionFormat": "html",
			"time": 1445694221840,
			"version": 2,
			"responses": [],
			"tests": "",
			"currentHelper": "normal",
			"helperAttributes": {},
			"folder": "7f762bcc-bcb9-b98a-a937-f2adc2e3124d"
		},
		{
			"id": "46504912-6514-fab2-804a-a0c4cf832884",
			"headers": "",
			"url": "http://95.85.59.29:1337/api/categories/:id",
			"pathVariables": {
				"id": null
			},
			"preRequestScript": "",
			"method": "GET",
			"collectionId": "e19de4e1-1cbf-d30a-7234-84672dad12c3",
			"data": [],
			"dataMode": "params",
			"name": "Get specific category",
			"description": "",
			"descriptionFormat": "html",
			"time": 1445694192860,
			"version": 2,
			"responses": [],
			"tests": "",
			"currentHelper": "normal",
			"helperAttributes": {},
			"folder": "7f762bcc-bcb9-b98a-a937-f2adc2e3124d"
		},
		{
			"id": "4a7d6965-fbe4-b0f6-9300-5aaff9a3eefc",
			"headers": "",
			"url": "http://95.85.59.29:1337/api/users/:id/tasks",
			"preRequestScript": "",
			"pathVariables": {
				"id": null
			},
			"method": "GET",
			"data": [],
			"dataMode": "params",
			"version": 2,
			"tests": "",
			"currentHelper": "normal",
			"helperAttributes": {},
			"time": 1445694261005,
			"name": "Get all tasks from one user",
			"description": "",
			"collectionId": "e19de4e1-1cbf-d30a-7234-84672dad12c3",
			"responses": []
		},
		{
			"id": "585d90d5-91d5-0f5e-7683-c284cd52dabf",
			"headers": "",
			"url": "http://95.85.59.29:1337/api/users/:id",
			"preRequestScript": "",
			"pathVariables": {
				"id": null
			},
			"method": "GET",
			"data": [],
			"dataMode": "params",
			"version": 2,
			"tests": "",
			"currentHelper": "normal",
			"helperAttributes": {},
			"time": 1445694264037,
			"name": "Get specific user",
			"description": "",
			"collectionId": "e19de4e1-1cbf-d30a-7234-84672dad12c3",
			"responses": []
		},
		{
			"id": "593e57d3-8737-3bcb-586d-dd4923b1f8ef",
			"headers": "Content-Type: application/json\n",
			"url": "http://95.85.59.29:1337/api/users/:userID/tasks/:taskID",
			"pathVariables": {
				"userID": null,
				"taskID": null
			},
			"preRequestScript": "",
			"method": "PUT",
			"collectionId": "e19de4e1-1cbf-d30a-7234-84672dad12c3",
			"data": [],
			"dataMode": "raw",
			"name": "Update task for a user",
			"description": "Use this to update a task's status...",
			"descriptionFormat": "html",
			"time": 1446328836246,
			"version": 2,
			"responses": [],
			"tests": "",
			"currentHelper": "normal",
			"helperAttributes": {},
			"folder": "7f762bcc-bcb9-b98a-a937-f2adc2e3124d",
			"rawModeData": "{\n    \"status\" : 2\n}"
		},
		{
			"id": "5d2d7bf8-2e32-a797-5997-f6fd675b8f0d",
			"headers": "Content-Type: application/json\n",
			"url": "http://95.85.59.29:1337/api/users",
			"preRequestScript": "",
			"pathVariables": {},
			"method": "POST",
			"data": [],
			"dataMode": "raw",
			"version": 2,
			"tests": "",
			"currentHelper": "normal",
			"helperAttributes": {},
			"time": 1445254141573,
			"name": "Add a new user",
			"description": "",
			"collectionId": "e19de4e1-1cbf-d30a-7234-84672dad12c3",
			"responses": [],
			"folder": "1dca47c6-0346-9fd3-5f90-9bd8211a800c",
			"rawModeData": "{\n    \"email\": \"gebruiker_100@gmail.com\",\n    \"token\": \"12345679abc\",\n    \"loginType\": \"facebook\",\n    \"tasks\": [\n      {\n        \"dueDate\": \"2015-10-13T13:18:49.002Z\",\n        \"challenge\": \"56224ab86dcac34e5e596a32\",\n        \"completed\": false\n      },\n      {\n        \"dueDate\": \"2015-10-14T13:18:49.003Z\",\n        \"challenge\": \"56224ab86dcac34e5e596a1c\",\n        \"completed\": false\n      }\n    ]\n}"
		},
		{
			"id": "695ae37b-7dd5-8e1b-9438-2728ebf7f8e7",
			"headers": "",
			"url": "http://95.85.59.29:1337/api/categories",
			"pathVariables": {},
			"preRequestScript": "",
			"method": "GET",
			"collectionId": "e19de4e1-1cbf-d30a-7234-84672dad12c3",
			"data": [],
			"dataMode": "params",
			"name": "Get all categories",
			"description": "",
			"descriptionFormat": "html",
			"time": 1445694155236,
			"version": 2,
			"responses": [],
			"tests": "",
			"currentHelper": "normal",
			"helperAttributes": {},
			"folder": "7f762bcc-bcb9-b98a-a937-f2adc2e3124d"
		},
		{
			"id": "7829ea83-b758-1854-9e89-9b8f1d0fc13e",
			"headers": "",
			"url": "http://95.85.59.29:1337/api/challenges/:id",
			"preRequestScript": "",
			"pathVariables": {
				"id": null
			},
			"method": "DELETE",
			"data": [],
			"dataMode": "params",
			"version": 2,
			"tests": "",
			"currentHelper": "normal",
			"helperAttributes": {},
			"time": 1445694245212,
			"name": "Delete challenge",
			"description": "",
			"collectionId": "e19de4e1-1cbf-d30a-7234-84672dad12c3",
			"responses": []
		},
		{
			"id": "7f2e7cad-0353-41f7-e30c-e94d8b8c7e57",
			"headers": "",
			"url": "http://95.85.59.29:1337/api/users/:id",
			"preRequestScript": "",
			"pathVariables": {
				"id": null
			},
			"method": "DELETE",
			"data": [],
			"dataMode": "params",
			"version": 2,
			"tests": "",
			"currentHelper": "normal",
			"helperAttributes": {},
			"time": 1445694257856,
			"name": "Delete user",
			"description": "",
			"collectionId": "e19de4e1-1cbf-d30a-7234-84672dad12c3",
			"responses": []
		},
		{
			"id": "b64bfb0b-12e0-a151-7bff-2df352876ca6",
			"headers": "",
			"url": "http://95.85.59.29:1337/api/users",
			"preRequestScript": "",
			"pathVariables": {},
			"method": "GET",
			"data": [],
			"dataMode": "params",
			"version": 2,
			"tests": "",
			"currentHelper": "normal",
			"helperAttributes": {},
			"time": 1445253556303,
			"name": "Get all users",
			"description": "",
			"collectionId": "e19de4e1-1cbf-d30a-7234-84672dad12c3",
			"responses": [],
			"folder": "1dca47c6-0346-9fd3-5f90-9bd8211a800c"
		},
		{
			"id": "cc3978f7-bc51-3215-76d5-5b4d69c7f6a0",
			"headers": "Content-Type: application/json\n",
			"url": "http://95.85.59.29:1337/api/users/:id",
			"preRequestScript": "",
			"pathVariables": {
				"id": null
			},
			"method": "PUT",
			"data": [],
			"dataMode": "raw",
			"version": 2,
			"tests": "",
			"currentHelper": "normal",
			"helperAttributes": {},
			"time": 1446322485773,
			"name": "Update user",
			"description": "",
			"collectionId": "e19de4e1-1cbf-d30a-7234-84672dad12c3",
			"responses": [],
			"rawModeData": "{\n    \"email\": \"newEmail@email.com\",\n    \"token\": \"newPassword\",\n    \"loginType\": \"newLoginType\"\n}"
		},
		{
			"id": "e4bb90c3-c4b7-b875-7664-69b797344d6d",
			"headers": "Content-Type: application/json\n",
			"url": "http://95.85.59.29:1337/api/challenges/562ba076ce597a91722bab2e",
			"preRequestScript": "",
			"pathVariables": {},
			"method": "PUT",
			"data": [],
			"dataMode": "raw",
			"version": 2,
			"tests": "",
			"currentHelper": "normal",
			"helperAttributes": {},
			"time": 1445776885752,
			"name": "Update challenge",
			"description": "",
			"collectionId": "e19de4e1-1cbf-d30a-7234-84672dad12c3",
			"responses": [],
			"rawModeData": "{\n    \"title\": \"DevTest :)\",\n    \"description\": \"DevTest :)\",\n    \"difficulty\": 2\n}"
		},
		{
			"id": "f02280a0-46d0-70c3-d945-58ab174095e5",
			"headers": "Content-Type: application/json\n",
			"url": "http://95.85.59.29:1337/api/categories/:id",
			"pathVariables": {
				"id": null
			},
			"preRequestScript": "",
			"method": "PUT",
			"collectionId": "e19de4e1-1cbf-d30a-7234-84672dad12c3",
			"data": [],
			"dataMode": "raw",
			"name": "Update category",
			"description": "",
			"descriptionFormat": "html",
			"time": 1445694381241,
			"version": 2,
			"responses": [],
			"tests": "",
			"currentHelper": "normal",
			"helperAttributes": {},
			"folder": "7f762bcc-bcb9-b98a-a937-f2adc2e3124d",
			"rawModeData": "{\n    \"name\": \"NewCategoryName\"\n}"
		},
		{
			"id": "f8f502e4-da76-237f-36ac-8facd2f2f782",
			"headers": "Content-Type: application/json\n",
			"url": "http://95.85.59.29:1337/api/challenges",
			"preRequestScript": "",
			"pathVariables": {},
			"method": "POST",
			"data": [],
			"dataMode": "raw",
			"version": 2,
			"tests": "",
			"currentHelper": "normal",
			"helperAttributes": {},
			"time": 1446322487459,
			"name": "Add a new challenge",
			"description": "",
			"collectionId": "e19de4e1-1cbf-d30a-7234-84672dad12c3",
			"responses": [],
			"rawModeData": " {\n    \"title\": \"Uitdaging #1\",\n    \"description\": \"Uitleg voor uitdaging #1\",\n    \"difficulty\": 1\n}"
		},
		{
			"id": "fc9d9a7b-4859-96be-cd8b-7d32b008f5e1",
			"headers": "Content-Type: application/json\n",
			"url": "http://95.85.59.29:1337/api/categories",
			"preRequestScript": "",
			"pathVariables": {},
			"method": "POST",
			"data": [],
			"dataMode": "raw",
			"version": 2,
			"tests": "",
			"currentHelper": "normal",
			"helperAttributes": {},
			"time": 1445694328266,
			"name": "Add a new category",
			"description": "",
			"collectionId": "e19de4e1-1cbf-d30a-7234-84672dad12c3",
			"responses": [],
			"rawModeData": "{\n    \"name\": \"Social\"\n}"
		},
		{
			"id": "fe02e771-9e6f-ad5e-5dfa-ed1e30be26e0",
			"headers": "",
			"url": "http://95.85.59.29:1337/api/challenges/:id",
			"preRequestScript": "",
			"pathVariables": {
				"id": null
			},
			"method": "GET",
			"data": [],
			"dataMode": "params",
			"version": 2,
			"tests": "",
			"currentHelper": "normal",
			"helperAttributes": {},
			"time": 1445694243927,
			"name": "Get specific challenge",
			"description": "",
			"collectionId": "e19de4e1-1cbf-d30a-7234-84672dad12c3",
			"responses": []
		}
	]
}